jax_grid_search/__init__.py
jax_grid_search/_gridding.py
jax_grid_search/_optimizers.py
jax_grid_search/_progressbar.py
jax_grid_search-0.2.0.dist-info/licenses/LICENSE
jax_grid_search-0.2.0.dist-info/METADATA
jax_grid_search-0.2.0.dist-info/WHEEL
jax_grid_search-0.2.0.dist-info/top_level.txt
jax_grid_search-0.2.0.dist-info/RECORD
