Metadata-Version: 2.4
Name: jax_grid_search
Version: 0.2.0
Summary: Distributed grid search in JAX
Author: Wassim Kabalan
License: MIT License
Project-URL: Homepage, https://github.com/CMBSciPol/jax-grid-search
Keywords: jax,hpc,gridding
Classifier: Development Status :: 4 - Beta
Classifier: Intended Audience :: Developers
Classifier: License :: OSI Approved :: GNU General Public License v3 (GPLv3)
Classifier: Programming Language :: Python :: 3
Classifier: Programming Language :: Python :: 3.10
Classifier: Programming Language :: Python :: 3.11
Classifier: Programming Language :: Python :: 3.12
Classifier: Programming Language :: Python :: 3 :: Only
Requires-Python: >=3.8
License-File: LICENSE
Requires-Dist: jax
Requires-Dist: tqdm
Requires-Dist: optax
Requires-Dist: jaxtyping
Requires-Dist: typing-extensions; python_version < "3.11"
Requires-Dist: rich
Provides-Extra: test
Requires-Dist: pytest; extra == "test"
Requires-Dist: pytest-cov; extra == "test"
Requires-Dist: pytest-mock; extra == "test"
Requires-Dist: chex; extra == "test"
Dynamic: license-file
